ipyrf/__init__.py
ipyrf/__main__.py
ipyrf/cli.py
ipyrf/controllers.py
ipyrf/interactive.py
ipyrf/logger.py
ipyrf/pacer.py
ipyrf/tcp.py
ipyrf/test.py
ipyrf/udp.py
ipyrf/utils.py
ipyrf-1.4.0.dist-info/licenses/LICENSE
ipyrf-1.4.0.dist-info/METADATA
ipyrf-1.4.0.dist-info/WHEEL
ipyrf-1.4.0.dist-info/entry_points.txt
ipyrf-1.4.0.dist-info/top_level.txt
ipyrf-1.4.0.dist-info/RECORD
