Metadata-Version: 2.4
Name: ipyrf
Version: 1.4.0
Summary: A tiny iperf3-like tool with JSON output (TCP/UDP)
Author: Steinwurf ApS
License: MIT License
Project-URL: Homepage, https://github.com/steinwurf/ipyrf
Project-URL: Repository, https://github.com/steinwurf/ipyrf
Project-URL: Issues, https://github.com/steinwurf/ipyrf/issues
Keywords: network,iperf,throughput,udp,tcp,benchmark
Classifier: Programming Language :: Python :: 3
Classifier: Programming Language :: Python :: 3 :: Only
Classifier: License :: OSI Approved :: MIT License
Classifier: Operating System :: POSIX :: Linux
Classifier: Topic :: System :: Networking
Classifier: Topic :: System :: Benchmark
Requires-Python: >=3.8
License-File: LICENSE
Provides-Extra: test
Requires-Dist: pytest>=7.0; extra == "test"
Requires-Dist: pytest-cov>=4.0; extra == "test"
Dynamic: license-file
